dante/__init__.py
dante/corpora.py
dante/danteshots.py
dante/dantestocks.py
dante/data/danteshots.csv
dante/data/dantestocks.csv
dante/data/danteshots/POS.conllu
dante/data/danteshots/annotated.conllu
dante/data/danteshots/base.csv
dante/data/danteshots/final_table.csv
dante/data/danteshots/pos.csv
dante/data/danteshots/stance.csv
dante/data/danteshots/table_freq.csv
dante/data/danteshots/table_freq_indi.csv
dante/data/danteshots/table_freq_tweet.csv
dante/data/dantestocks/POS.conllu
dante/data/dantestocks/annotated.conllu
dante/data/dantestocks/base.csv
dante/data/dantestocks/emotion.csv
dante/data/dantestocks/final_table.csv
dante/data/dantestocks/pos.csv
dante/data/dantestocks/table_freq.csv
dante/data/dantestocks/table_freq_indi.csv
dante/data/dantestocks/table_freq_tweet.csv
dante/data/petrogold/annotated.conllu
dante/data/petrogold/final_table.csv
dante/data/petrogold/table_freq.csv
dante/data/petrogold/table_freq_tweet.csv
dante/data/portinari/annotated.conllu
dante/data/portinari/final_table.csv
dante/data/portinari/table_freq.csv
dante/data/portinari/table_freq_tweet.csv
dante/data/porttinari/annotated.conllu
dante/data/porttinari/final_table.csv
dante/data/porttinari/table_freq.csv
dante/data/porttinari/table_freq_tweet.csv
dante_corpora-2.0.5.dist-info/LICENSE
dante_corpora-2.0.5.dist-info/METADATA
dante_corpora-2.0.5.dist-info/WHEEL
dante_corpora-2.0.5.dist-info/top_level.txt
dante_corpora-2.0.5.dist-info/RECORD
