Metadata-Version: 2.1
Name: dante-corpora
Version: 2.0.5
Summary: Pacote Python contendo os corpora do projeto DANTE do POeTiSA
Author: felmateos
Author-email: felmateos@gmail.com
License: MIT
License-File: LICENSE
Requires-Dist: pandas ==2.2.2
